Metadata-Version: 2.1
Name: eyediagram
Version: 0.1.2
Summary: Tools for plotting an eye diagram.
Home-page: UNKNOWN
Author: Warren Weckesser
License: BSD
Platform: UNKNOWN
Classifier: License :: OSI Approved :: BSD License
Classifier: Intended Audience :: Developers
Classifier: Operating System :: OS Independent
Classifier: Programming Language :: Python
